[{"track_isrc": "GBUM71404104", "has_lyrics": 1, "instrumental": 0, "explicit": 1, "genres": {"music_genre_list": [{"music_genre": {"music_genre_id": 10, "music_genre_parent_id": 34, "music_genre_name": "Singer/Songwriter", "music_genre_name_extended": "Singer/Songwriter", "music_genre_vanity": "Singer-Songwriter"}}, {"music_genre": {"music_genre_id": 21, "music_genre_parent_id": 34, "music_genre_name": "Rock", "music_genre_name_extended": "Rock", "music_genre_vanity": "Rock"}}]}}, {"track_isrc": "USWD11569827", "has_lyrics": 1, "instrumental": 0, "explicit": 0, "genres": {"music_genre_list": [{"music_genre": {"music_genre_id": 4, "music_genre_parent_id": 34, "music_genre_name": "Children's Music", "music_genre_name_extended": "Children's Music", "music_genre_vanity": "Children's-Music"}}, {"music_genre": {"music_genre_id": 16, "music_genre_parent_id": 34, "music_genre_name": "Soundtrack", "music_genre_name_extended": "Soundtrack", "music_genre_vanity": "Soundtrack"}}]}}, {"track_isrc": "GBBKS1600071", "has_lyrics": 1, "instrumental": 0, "explicit": 0, "genres": {"music_genre_list": [{"music_genre": {"music_genre_id": 20, "music_genre_parent_id": 34, "music_genre_name": "Alternative", "music_genre_name_extended": "Alternative", "music_genre_vanity": "Alternative"}}]}}, {"track_isrc": "USSM17500025", "has_lyrics": 1, "instrumental": 0, "explicit": 0, "genres": {"music_genre_list": [{"music_genre": {"music_genre_id": 15, "music_genre_parent_id": 34, "music_genre_name": "R&B/Soul", "music_genre_name_extended": "R&B/Soul", "music_genre_vanity": "R-B-Soul"}}]}}, {"track_isrc": "USZ4V1500129", "has_lyrics": 1, "instrumental": 0, "explicit": 0, "genres": {"music_genre_list": [{"music_genre": {"music_genre_id": 1058, "music_genre_parent_id": 7, "music_genre_name": "Electronica", "music_genre_name_extended": "Electronic / Electronica", "music_genre_vanity": "Electronic-Electronica"}}, {"music_genre": {"music_genre_id": 7, "music_genre_parent_id": 34, "music_genre_name": "Electronic", "music_genre_name_extended": "Electronic", "music_genre_vanity": "Electronic"}}]}}, {"track_isrc": "USUM71101928", "has_lyrics": 1, "instrumental": 0, "explicit": 0, "genres": {"music_genre_list": []}}, {"track_isrc": "USUM70981907", "has_lyrics": 1, "instrumental": 0, "explicit": 1, "genres": {"music_genre_list": [{"music_genre": {"music_genre_id": 18, "music_genre_parent_id": 34, "music_genre_name": "Hip Hop/Rap", "music_genre_name_extended": "Hip-Hop/Rap", "music_genre_vanity": "Hip-Hop-Rap"}}]}}, {"track_isrc": "USAT21100921", "has_lyrics": 1, "instrumental": 0, "explicit": 0, "genres": {"music_genre_list": [{"music_genre": {"music_genre_id": 20, "music_genre_parent_id": 34, "music_genre_name": "Alternative", "music_genre_name_extended": "Alternative", "music_genre_vanity": "Alternative"}}, {"music_genre": {"music_genre_id": 21, "music_genre_parent_id": 34, "music_genre_name": "Rock", "music_genre_name_extended": "Rock", "music_genre_vanity": "Rock"}}]}}, {"track_isrc": "USJI10700087", "has_lyrics": 1, "instrumental": 0, "explicit": 0, "genres": {"music_genre_list": [{"music_genre": {"music_genre_id": 18, "music_genre_parent_id": 34, "music_genre_name": "Hip Hop/Rap", "music_genre_name_extended": "Hip-Hop/Rap", "music_genre_vanity": "Hip-Hop-Rap"}}]}}, {"track_isrc": "US4HB1200011", "has_lyrics": 1, "instrumental": 0, "explicit": 0, "genres": {"music_genre_list": [{"music_genre": {"music_genre_id": 14, "music_genre_parent_id": 34, "music_genre_name": "Pop", "music_genre_name_extended": "Pop", "music_genre_vanity": "Pop"}}]}}, {"track_isrc": "GBAWA0513434", "has_lyrics": 1, "instrumental": 0, "explicit": 0, "genres": {"music_genre_list": [{"music_genre": {"music_genre_id": 6, "music_genre_parent_id": 34, "music_genre_name": "Country", "music_genre_name_extended": "Country", "music_genre_vanity": "Country"}}]}}, {"track_isrc": "USUM71027315", "has_lyrics": 1, "instrumental": 0, "explicit": 1, "genres": {"music_genre_list": [{"music_genre": {"music_genre_id": 18, "music_genre_parent_id": 34, "music_genre_name": "Hip Hop/Rap", "music_genre_name_extended": "Hip-Hop/Rap", "music_genre_vanity": "Hip-Hop-Rap"}}]}}, {"track_isrc": "GBKQU1627929", "has_lyrics": 1, "instrumental": 0, "explicit": 0, "genres": {"music_genre_list": [{"music_genre": {"music_genre_id": 1048, "music_genre_parent_id": 17, "music_genre_name": "House", "music_genre_name_extended": "Dance / House", "music_genre_vanity": "Dance-House"}}]}}, {"track_isrc": "USSM11603675", "has_lyrics": 1, "instrumental": 0, "explicit": 1, "genres": {"music_genre_list": [{"music_genre": {"music_genre_id": 16, "music_genre_parent_id": 34, "music_genre_name": "Soundtrack", "music_genre_name_extended": "Soundtrack", "music_genre_vanity": "Soundtrack"}}]}}, {"track_isrc": "USUM70967699", "has_lyrics": 1, "instrumental": 0, "explicit": 1, "genres": {"music_genre_list": [{"music_genre": {"music_genre_id": 14, "music_genre_parent_id": 34, "music_genre_name": "Pop", "music_genre_name_extended": "Pop", "music_genre_vanity": "Pop"}}]}}, {"track_isrc": "USAM19800328", "has_lyrics": 1, "instrumental": 0, "explicit": 1, "genres": {"music_genre_list": [{"music_genre": {"music_genre_id": 21, "music_genre_parent_id": 34, "music_genre_name": "Rock", "music_genre_name_extended": "Rock", "music_genre_vanity": "Rock"}}]}}, {"track_isrc": "USAT21700378", "has_lyrics": 1, "instrumental": 0, "explicit": 1, "genres": {"music_genre_list": [{"music_genre": {"music_genre_id": 18, "music_genre_parent_id": 34, "music_genre_name": "Hip Hop/Rap", "music_genre_name_extended": "Hip-Hop/Rap", "music_genre_vanity": "Hip-Hop-Rap"}}]}}, {"track_isrc": "USUM71205353", "has_lyrics": 1, "instrumental": 0, "explicit": 1, "genres": {"music_genre_list": [{"music_genre": {"music_genre_id": 14, "music_genre_parent_id": 34, "music_genre_name": "Pop", "music_genre_name_extended": "Pop", "music_genre_vanity": "Pop"}}]}}, {"track_isrc": "USUM71412828", "has_lyrics": 1, "instrumental": 0, "explicit": 0, "genres": {"music_genre_list": [{"music_genre": {"music_genre_id": 14, "music_genre_parent_id": 34, "music_genre_name": "Pop", "music_genre_name_extended": "Pop", "music_genre_vanity": "Pop"}}]}}, {"track_isrc": "USSM11302483", "has_lyrics": 1, "instrumental": 0, "explicit": 0, "genres": {"music_genre_list": [{"music_genre": {"music_genre_id": 14, "music_genre_parent_id": 34, "music_genre_name": "Pop", "music_genre_name_extended": "Pop", "music_genre_vanity": "Pop"}}]}}, {"track_isrc": "USUL10500195", "has_lyrics": 1, "instrumental": 0, "explicit": 0, "genres": {"music_genre_list": [{"music_genre": {"music_genre_id": 1119, "music_genre_parent_id": 12, "music_genre_name": "Latin Urban", "music_genre_name_extended": "Latin / Latin Urban", "music_genre_vanity": "Latin-Latin-Urban"}}]}}, {"track_isrc": "USWB10302758", "has_lyrics": 1, "instrumental": 0, "explicit": 0, "genres": {"music_genre_list": [{"music_genre": {"music_genre_id": 6, "music_genre_parent_id": 34, "music_genre_name": "Country", "music_genre_name_extended": "Country", "music_genre_vanity": "Country"}}]}}, {"track_isrc": "USKO11401483", "has_lyrics": 1, "instrumental": 0, "explicit": 0, "genres": {"music_genre_list": [{"music_genre": {"music_genre_id": 15, "music_genre_parent_id": 34, "music_genre_name": "R&B/Soul", "music_genre_name_extended": "R&B/Soul", "music_genre_vanity": "R-B-Soul"}}]}}, {"track_isrc": "USAN20900072", "has_lyrics": 1, "instrumental": 0, "explicit": 0, "genres": {"music_genre_list": [{"music_genre": {"music_genre_id": 6, "music_genre_parent_id": 34, "music_genre_name": "Country", "music_genre_name_extended": "Country", "music_genre_vanity": "Country"}}]}}, {"track_isrc": "USZXT1108633", "has_lyrics": 1, "instrumental": 0, "explicit": 0, "genres": {"music_genre_list": [{"music_genre": {"music_genre_id": 14, "music_genre_parent_id": 34, "music_genre_name": "Pop", "music_genre_name_extended": "Pop", "music_genre_vanity": "Pop"}}]}}, {"track_isrc": "USVG29652600", "has_lyrics": 1, "instrumental": 0, "explicit": 1, "genres": {"music_genre_list": [{"music_genre": {"music_genre_id": 10, "music_genre_parent_id": 34, "music_genre_name": "Singer/Songwriter", "music_genre_name_extended": "Singer/Songwriter", "music_genre_vanity": "Singer-Songwriter"}}]}}, {"track_isrc": "USRC11200465", "has_lyrics": 1, "instrumental": 0, "explicit": 0, "genres": {"music_genre_list": [{"music_genre": {"music_genre_id": 15, "music_genre_parent_id": 34, "music_genre_name": "R&B/Soul", "music_genre_name_extended": "R&B/Soul", "music_genre_vanity": "R-B-Soul"}}]}}, {"track_isrc": "USUG11500395", "has_lyrics": 1, "instrumental": 0, "explicit": 0, "genres": {"music_genre_list": [{"music_genre": {"music_genre_id": 20, "music_genre_parent_id": 34, "music_genre_name": "Alternative", "music_genre_name_extended": "Alternative", "music_genre_vanity": "Alternative"}}]}}, {"track_isrc": "USAR10301423", "has_lyrics": 1, "instrumental": 0, "explicit": 1, "genres": {"music_genre_list": [{"music_genre": {"music_genre_id": 14, "music_genre_parent_id": 34, "music_genre_name": "Pop", "music_genre_name_extended": "Pop", "music_genre_vanity": "Pop"}}]}}, {"track_isrc": "USUM71204501", "has_lyrics": 1, "instrumental": 0, "explicit": 0, "genres": {"music_genre_list": [{"music_genre": {"music_genre_id": 1133, "music_genre_parent_id": 14, "music_genre_name": "Pop/Rock", "music_genre_name_extended": "Pop / Pop/Rock", "music_genre_vanity": "Pop-Pop-Rock"}}, {"music_genre": {"music_genre_id": 14, "music_genre_parent_id": 34, "music_genre_name": "Pop", "music_genre_name_extended": "Pop", "music_genre_vanity": "Pop"}}]}}, {"track_isrc": "USCN11100180", "has_lyrics": 1, "instrumental": 0, "explicit": 0, "genres": {"music_genre_list": [{"music_genre": {"music_genre_id": 1133, "music_genre_parent_id": 14, "music_genre_name": "Pop/Rock", "music_genre_name_extended": "Pop / Pop/Rock", "music_genre_vanity": "Pop-Pop-Rock"}}, {"music_genre": {"music_genre_id": 1037, "music_genre_parent_id": 6, "music_genre_name": "Contemporary Country", "music_genre_name_extended": "Country / Contemporary Country", "music_genre_vanity": "Country-Contemporary-Country"}}, {"music_genre": {"music_genre_id": 14, "music_genre_parent_id": 34, "music_genre_name": "Pop", "music_genre_name_extended": "Pop", "music_genre_vanity": "Pop"}}, {"music_genre": {"music_genre_id": 6, "music_genre_parent_id": 34, "music_genre_name": "Country", "music_genre_name_extended": "Country", "music_genre_vanity": "Country"}}]}}, {"track_isrc": "GBUM71302626", "has_lyrics": 1, "instrumental": 0, "explicit": 0, "genres": {"music_genre_list": [{"music_genre": {"music_genre_id": 100007, "music_genre_parent_id": 5, "music_genre_name": "Electronic", "music_genre_name_extended": "Classical / Electronic", "music_genre_vanity": "Classic-Electronic"}}, {"music_genre": {"music_genre_id": 7, "music_genre_parent_id": 34, "music_genre_name": "Electronic", "music_genre_name_extended": "Electronic", "music_genre_vanity": "Electronic"}}]}}, {"track_isrc": "USLN60800006", "has_lyrics": 1, "instrumental": 0, "explicit": 0, "genres": {"music_genre_list": [{"music_genre": {"music_genre_id": 21, "music_genre_parent_id": 34, "music_genre_name": "Rock", "music_genre_name_extended": "Rock", "music_genre_vanity": "Rock"}}]}}, {"track_isrc": "GBAMC9700004", "has_lyrics": 1, "instrumental": 0, "explicit": 0, "genres": {"music_genre_list": [{"music_genre": {"music_genre_id": 1152, "music_genre_parent_id": 21, "music_genre_name": "Hard Rock", "music_genre_name_extended": "Rock / Hard Rock", "music_genre_vanity": "Rock-Hard-Rock"}}, {"music_genre": {"music_genre_id": 21, "music_genre_parent_id": 34, "music_genre_name": "Rock", "music_genre_name_extended": "Rock", "music_genre_vanity": "Rock"}}]}}, {"track_isrc": "USCM51400355", "has_lyrics": 1, "instrumental": 0, "explicit": 1, "genres": {"music_genre_list": [{"music_genre": {"music_genre_id": 14, "music_genre_parent_id": 34, "music_genre_name": "Pop", "music_genre_name_extended": "Pop", "music_genre_vanity": "Pop"}}]}}, {"track_isrc": "GBAYE1500979", "has_lyrics": 1, "instrumental": 0, "explicit": 0, "genres": {"music_genre_list": [{"music_genre": {"music_genre_id": 1122, "music_genre_parent_id": 34, "music_genre_name": "Brazilian", "music_genre_name_extended": "Brazilian", "music_genre_vanity": "Brazilian"}}]}}, {"track_isrc": "USUM71500676", "has_lyrics": 1, "instrumental": 0, "explicit": 0, "genres": {"music_genre_list": [{"music_genre": {"music_genre_id": 6, "music_genre_parent_id": 34, "music_genre_name": "Country", "music_genre_name_extended": "Country", "music_genre_vanity": "Country"}}]}}, {"track_isrc": "GBCTA1200022", "has_lyrics": 1, "instrumental": 0, "explicit": 0, "genres": {"music_genre_list": [{"music_genre": {"music_genre_id": 1037, "music_genre_parent_id": 6, "music_genre_name": "Contemporary Country", "music_genre_name_extended": "Country / Contemporary Country", "music_genre_vanity": "Country-Contemporary-Country"}}, {"music_genre": {"music_genre_id": 6, "music_genre_parent_id": 34, "music_genre_name": "Country", "music_genre_name_extended": "Country", "music_genre_vanity": "Country"}}]}}, {"track_isrc": "USSM11609208", "has_lyrics": 1, "instrumental": 0, "explicit": 0, "genres": {"music_genre_list": [{"music_genre": {"music_genre_id": 14, "music_genre_parent_id": 34, "music_genre_name": "Pop", "music_genre_name_extended": "Pop", "music_genre_vanity": "Pop"}}]}}, {"track_isrc": "USUM70753390", "has_lyrics": 1, "instrumental": 0, "explicit": 1, "genres": {"music_genre_list": [{"music_genre": {"music_genre_id": 12, "music_genre_parent_id": 34, "music_genre_name": "Latin", "music_genre_name_extended": "Latin", "music_genre_vanity": "Latin"}}]}}, {"track_isrc": "USRC11601072", "has_lyrics": 1, "instrumental": 0, "explicit": 1, "genres": {"music_genre_list": [{"music_genre": {"music_genre_id": 14, "music_genre_parent_id": 34, "music_genre_name": "Pop", "music_genre_name_extended": "Pop", "music_genre_vanity": "Pop"}}]}}, {"track_isrc": "USA6P0499036", "has_lyrics": 1, "instrumental": 0, "explicit": 1, "genres": {"music_genre_list": [{"music_genre": {"music_genre_id": 20, "music_genre_parent_id": 34, "music_genre_name": "Alternative", "music_genre_name_extended": "Alternative", "music_genre_vanity": "Alternative"}}]}}, {"track_isrc": "GB2H71600046", "has_lyrics": 1, "instrumental": 0, "explicit": 0, "genres": {"music_genre_list": [{"music_genre": {"music_genre_id": 1004, "music_genre_parent_id": 20, "music_genre_name": "Indie Rock", "music_genre_name_extended": "Alternative / Indie Rock", "music_genre_vanity": "Alternative-Indie-Rock"}}, {"music_genre": {"music_genre_id": 14, "music_genre_parent_id": 34, "music_genre_name": "Pop", "music_genre_name_extended": "Pop", "music_genre_vanity": "Pop"}}]}}, {"track_isrc": "USSM11401645", "has_lyrics": 1, "instrumental": 0, "explicit": 0, "genres": {"music_genre_list": [{"music_genre": {"music_genre_id": 20, "music_genre_parent_id": 34, "music_genre_name": "Alternative", "music_genre_name_extended": "Alternative", "music_genre_vanity": "Alternative"}}]}}, {"track_isrc": "GBCTA1500061", "has_lyrics": 1, "instrumental": 0, "explicit": 0, "genres": {"music_genre_list": [{"music_genre": {"music_genre_id": 1037, "music_genre_parent_id": 6, "music_genre_name": "Contemporary Country", "music_genre_name_extended": "Country / Contemporary Country", "music_genre_vanity": "Country-Contemporary-Country"}}, {"music_genre": {"music_genre_id": 1136, "music_genre_parent_id": 15, "music_genre_name": "Contemporary R&B", "music_genre_name_extended": "R&B/Soul / Contemporary R&B", "music_genre_vanity": "R-B-Soul-Contemporary-R-B"}}, {"music_genre": {"music_genre_id": 6, "music_genre_parent_id": 34, "music_genre_name": "Country", "music_genre_name_extended": "Country", "music_genre_vanity": "Country"}}]}}, {"track_isrc": "USUM50511921", "has_lyrics": 1, "instrumental": 0, "explicit": 1, "genres": {"music_genre_list": [{"music_genre": {"music_genre_id": 1119, "music_genre_parent_id": 12, "music_genre_name": "Latin Urban", "music_genre_name_extended": "Latin / Latin Urban", "music_genre_vanity": "Latin-Latin-Urban"}}, {"music_genre": {"music_genre_id": 1183, "music_genre_parent_id": 24, "music_genre_name": "Dancehall", "music_genre_name_extended": "Reggae / Dancehall", "music_genre_vanity": "Reggae-Dancehall"}}, {"music_genre": {"music_genre_id": 12, "music_genre_parent_id": 34, "music_genre_name": "Latin", "music_genre_name_extended": "Latin", "music_genre_vanity": "Latin"}}, {"music_genre": {"music_genre_id": 24, "music_genre_parent_id": 34, "music_genre_name": "Reggae", "music_genre_name_extended": "Reggae", "music_genre_vanity": "Reggae"}}]}}, {"track_isrc": "USSM11703956", "has_lyrics": 1, "instrumental": 0, "explicit": 0, "genres": {"music_genre_list": [{"music_genre": {"music_genre_id": 1289, "music_genre_parent_id": 34, "music_genre_name": "Folk", "music_genre_name_extended": "Folk", "music_genre_vanity": "Folk"}}]}}, {"track_isrc": "USIR10110209", "has_lyrics": 1, "instrumental": 0, "explicit": 1, "genres": {"music_genre_list": [{"music_genre": {"music_genre_id": 18, "music_genre_parent_id": 34, "music_genre_name": "Hip Hop/Rap", "music_genre_name_extended": "Hip-Hop/Rap", "music_genre_vanity": "Hip-Hop-Rap"}}]}}, {"track_isrc": "QM4MA1500018", "has_lyrics": 1, "instrumental": 0, "explicit": 0, "genres": {"music_genre_list": [{"music_genre": {"music_genre_id": 6, "music_genre_parent_id": 34, "music_genre_name": "Country", "music_genre_name_extended": "Country", "music_genre_vanity": "Country"}}]}}, {"track_isrc": "US25L1400043", "has_lyrics": 1, "instrumental": 0, "explicit": 0, "genres": {"music_genre_list": [{"music_genre": {"music_genre_id": 22, "music_genre_parent_id": 34, "music_genre_name": "Christian & Gospel", "music_genre_name_extended": "Christian & Gospel", "music_genre_vanity": "Christian-Gospel"}}]}}, {"track_isrc": "USAT21601721", "has_lyrics": 1, "instrumental": 0, "explicit": 1, "genres": {"music_genre_list": [{"music_genre": {"music_genre_id": 1073, "music_genre_parent_id": 18, "music_genre_name": "Hip-Hop", "music_genre_name_extended": "Hip Hop/Rap / Hip-Hop", "music_genre_vanity": "Hip-Hop-Rap-Hip-Hop"}}, {"music_genre": {"music_genre_id": 18, "music_genre_parent_id": 34, "music_genre_name": "Hip Hop/Rap", "music_genre_name_extended": "Hip-Hop/Rap", "music_genre_vanity": "Hip-Hop-Rap"}}]}}, {"track_isrc": "USAT21602646", "has_lyrics": 1, "instrumental": 0, "explicit": 1, "genres": {"music_genre_list": [{"music_genre": {"music_genre_id": 14, "music_genre_parent_id": 34, "music_genre_name": "Pop", "music_genre_name_extended": "Pop", "music_genre_vanity": "Pop"}}]}}, {"track_isrc": "USHF31508605", "has_lyrics": 1, "instrumental": 0, "explicit": 0, "genres": {"music_genre_list": [{"music_genre": {"music_genre_id": 1004, "music_genre_parent_id": 20, "music_genre_name": "Indie Rock", "music_genre_name_extended": "Alternative / Indie Rock", "music_genre_vanity": "Alternative-Indie-Rock"}}, {"music_genre": {"music_genre_id": 20, "music_genre_parent_id": 34, "music_genre_name": "Alternative", "music_genre_name_extended": "Alternative", "music_genre_vanity": "Alternative"}}]}}, {"track_isrc": "TCACJ1564367", "has_lyrics": 1, "instrumental": 0, "explicit": 0, "genres": {"music_genre_list": [{"music_genre": {"music_genre_id": 7, "music_genre_parent_id": 34, "music_genre_name": "Electronic", "music_genre_name_extended": "Electronic", "music_genre_vanity": "Electronic"}}]}}, {"track_isrc": "GBAHS1100350", "has_lyrics": 1, "instrumental": 0, "explicit": 1, "genres": {"music_genre_list": [{"music_genre": {"music_genre_id": 20, "music_genre_parent_id": 34, "music_genre_name": "Alternative", "music_genre_name_extended": "Alternative", "music_genre_vanity": "Alternative"}}]}}, {"track_isrc": "US3R40713505", "has_lyrics": 1, "instrumental": 0, "explicit": 0, "genres": {"music_genre_list": [{"music_genre": {"music_genre_id": 14, "music_genre_parent_id": 34, "music_genre_name": "Pop", "music_genre_name_extended": "Pop", "music_genre_vanity": "Pop"}}]}}, {"track_isrc": "USUM71603065", "has_lyrics": 1, "instrumental": 0, "explicit": 1, "genres": {"music_genre_list": [{"music_genre": {"music_genre_id": 1101, "music_genre_parent_id": 22, "music_genre_name": "Gospel", "music_genre_name_extended": "Christian & Gospel / Gospel", "music_genre_vanity": "Christian-Gospel-Gospel"}}, {"music_genre": {"music_genre_id": 18, "music_genre_parent_id": 34, "music_genre_name": "Hip Hop/Rap", "music_genre_name_extended": "Hip-Hop/Rap", "music_genre_vanity": "Hip-Hop-Rap"}}]}}, {"track_isrc": "GBCTA1500057", "has_lyrics": 1, "instrumental": 0, "explicit": 0, "genres": {"music_genre_list": [{"music_genre": {"music_genre_id": 1037, "music_genre_parent_id": 6, "music_genre_name": "Contemporary Country", "music_genre_name_extended": "Country / Contemporary Country", "music_genre_vanity": "Country-Contemporary-Country"}}, {"music_genre": {"music_genre_id": 6, "music_genre_parent_id": 34, "music_genre_name": "Country", "music_genre_name_extended": "Country", "music_genre_vanity": "Country"}}]}}, {"track_isrc": "GBUM71700717", "has_lyrics": 1, "instrumental": 0, "explicit": 0, "genres": {"music_genre_list": [{"music_genre": {"music_genre_id": 20, "music_genre_parent_id": 34, "music_genre_name": "Alternative", "music_genre_name_extended": "Alternative", "music_genre_vanity": "Alternative"}}]}}, {"track_isrc": "USHR11435916", "has_lyrics": 1, "instrumental": 0, "explicit": 0, "genres": {"music_genre_list": [{"music_genre": {"music_genre_id": 1135, "music_genre_parent_id": 14, "music_genre_name": "Teen Pop", "music_genre_name_extended": "Pop / Teen Pop", "music_genre_vanity": "Pop-Teen-Pop"}}, {"music_genre": {"music_genre_id": 14, "music_genre_parent_id": 34, "music_genre_name": "Pop", "music_genre_name_extended": "Pop", "music_genre_vanity": "Pop"}}]}}, {"track_isrc": "USHF31609503", "has_lyrics": 1, "instrumental": 0, "explicit": 0, "genres": {"music_genre_list": [{"music_genre": {"music_genre_id": 20, "music_genre_parent_id": 34, "music_genre_name": "Alternative", "music_genre_name_extended": "Alternative", "music_genre_vanity": "Alternative"}}]}}, {"track_isrc": "USA2A0301915", "has_lyrics": 1, "instrumental": 0, "explicit": 0, "genres": {"music_genre_list": [{"music_genre": {"music_genre_id": 1063, "music_genre_parent_id": 10, "music_genre_name": "Contemporary Folk", "music_genre_name_extended": "Singer/Songwriter / Contemporary Folk", "music_genre_vanity": "Singer-Songwriter-Contemporary-Folk"}}, {"music_genre": {"music_genre_id": 6, "music_genre_parent_id": 34, "music_genre_name": "Country", "music_genre_name_extended": "Country", "music_genre_vanity": "Country"}}]}}, {"track_isrc": "GBHMU1400029", "has_lyrics": 1, "instrumental": 0, "explicit": 1, "genres": {"music_genre_list": [{"music_genre": {"music_genre_id": 14, "music_genre_parent_id": 34, "music_genre_name": "Pop", "music_genre_name_extended": "Pop", "music_genre_vanity": "Pop"}}]}}, {"track_isrc": "TCACU1691468", "has_lyrics": 1, "instrumental": 0, "explicit": 0, "genres": {"music_genre_list": [{"music_genre": {"music_genre_id": 10, "music_genre_parent_id": 34, "music_genre_name": "Singer/Songwriter", "music_genre_name_extended": "Singer/Songwriter", "music_genre_vanity": "Singer-Songwriter"}}]}}, {"track_isrc": "USGOT0403060", "has_lyrics": 1, "instrumental": 0, "explicit": 0, "genres": {"music_genre_list": [{"music_genre": {"music_genre_id": 18, "music_genre_parent_id": 34, "music_genre_name": "Hip Hop/Rap", "music_genre_name_extended": "Hip-Hop/Rap", "music_genre_vanity": "Hip-Hop-Rap"}}]}}, {"track_isrc": "USUM71418084", "has_lyrics": 1, "instrumental": 0, "explicit": 0, "genres": {"music_genre_list": [{"music_genre": {"music_genre_id": 1042, "music_genre_parent_id": 6, "music_genre_name": "Traditional Country", "music_genre_name_extended": "Country / Traditional Country", "music_genre_vanity": "Country-Traditional-Country"}}, {"music_genre": {"music_genre_id": 6, "music_genre_parent_id": 34, "music_genre_name": "Country", "music_genre_name_extended": "Country", "music_genre_vanity": "Country"}}]}}, {"track_isrc": "USSM11001184", "has_lyrics": 1, "instrumental": 0, "explicit": 0, "genres": {"music_genre_list": [{"music_genre": {"music_genre_id": 20, "music_genre_parent_id": 34, "music_genre_name": "Alternative", "music_genre_name_extended": "Alternative", "music_genre_vanity": "Alternative"}}]}}, {"track_isrc": "USSM18600320", "has_lyrics": 1, "instrumental": 0, "explicit": 0, "genres": {"music_genre_list": [{"music_genre": {"music_genre_id": 15, "music_genre_parent_id": 34, "music_genre_name": "R&B/Soul", "music_genre_name_extended": "R&B/Soul", "music_genre_vanity": "R-B-Soul"}}]}}, {"track_isrc": "US4M30701909", "has_lyrics": 1, "instrumental": 0, "explicit": 1, "genres": {"music_genre_list": [{"music_genre": {"music_genre_id": 1004, "music_genre_parent_id": 20, "music_genre_name": "Indie Rock", "music_genre_name_extended": "Alternative / Indie Rock", "music_genre_vanity": "Alternative-Indie-Rock"}}, {"music_genre": {"music_genre_id": 1144, "music_genre_parent_id": 21, "music_genre_name": "Adult Alternative", "music_genre_name_extended": "Rock / Adult Alternative", "music_genre_vanity": "Rock-Adult-Alternative"}}, {"music_genre": {"music_genre_id": 20, "music_genre_parent_id": 34, "music_genre_name": "Alternative", "music_genre_name_extended": "Alternative", "music_genre_vanity": "Alternative"}}]}}, {"track_isrc": "TCABS1317955", "has_lyrics": 1, "instrumental": 0, "explicit": 0, "genres": {"music_genre_list": [{"music_genre": {"music_genre_id": 15, "music_genre_parent_id": 34, "music_genre_name": "R&B/Soul", "music_genre_name_extended": "R&B/Soul", "music_genre_vanity": "R-B-Soul"}}]}}, {"track_isrc": "GBUM71111565", "has_lyrics": 1, "instrumental": 0, "explicit": 0, "genres": {"music_genre_list": [{"music_genre": {"music_genre_id": 14, "music_genre_parent_id": 34, "music_genre_name": "Pop", "music_genre_name_extended": "Pop", "music_genre_vanity": "Pop"}}, {"music_genre": {"music_genre_id": 20, "music_genre_parent_id": 34, "music_genre_name": "Alternative", "music_genre_name_extended": "Alternative", "music_genre_vanity": "Alternative"}}, {"music_genre": {"music_genre_id": 1057, "music_genre_parent_id": 7, "music_genre_name": "Downtempo", "music_genre_name_extended": "Electronic / Downtempo", "music_genre_vanity": "Electronic-Downtempo"}}]}}, {"track_isrc": "FR6V80893867", "has_lyrics": 1, "instrumental": 0, "explicit": 0, "genres": {"music_genre_list": [{"music_genre": {"music_genre_id": 7, "music_genre_parent_id": 34, "music_genre_name": "Electronic", "music_genre_name_extended": "Electronic", "music_genre_vanity": "Electronic"}}]}}, {"track_isrc": "USAT21001508", "has_lyrics": 1, "instrumental": 0, "explicit": 0, "genres": {"music_genre_list": [{"music_genre": {"music_genre_id": 1134, "music_genre_parent_id": 14, "music_genre_name": "Soft Rock", "music_genre_name_extended": "Pop / Soft Rock", "music_genre_vanity": "Pop-Soft-Rock"}}, {"music_genre": {"music_genre_id": 14, "music_genre_parent_id": 34, "music_genre_name": "Pop", "music_genre_name_extended": "Pop", "music_genre_vanity": "Pop"}}]}}, {"track_isrc": "USAN21100006", "has_lyrics": 1, "instrumental": 0, "explicit": 0, "genres": {"music_genre_list": [{"music_genre": {"music_genre_id": 1042, "music_genre_parent_id": 6, "music_genre_name": "Traditional Country", "music_genre_name_extended": "Country / Traditional Country", "music_genre_vanity": "Country-Traditional-Country"}}]}}, {"track_isrc": "USRN11400223", "has_lyrics": 1, "instrumental": 0, "explicit": 0, "genres": {"music_genre_list": [{"music_genre": {"music_genre_id": 1042, "music_genre_parent_id": 6, "music_genre_name": "Traditional Country", "music_genre_name_extended": "Country / Traditional Country", "music_genre_vanity": "Country-Traditional-Country"}}, {"music_genre": {"music_genre_id": 6, "music_genre_parent_id": 34, "music_genre_name": "Country", "music_genre_name_extended": "Country", "music_genre_vanity": "Country"}}]}}, {"track_isrc": "USAT21701726", "has_lyrics": 1, "instrumental": 0, "explicit": 1, "genres": {"music_genre_list": [{"music_genre": {"music_genre_id": 1069, "music_genre_parent_id": 18, "music_genre_name": "Dirty South", "music_genre_name_extended": "Hip Hop/Rap / Dirty South", "music_genre_vanity": "Hip-Hop-Rap-Dirty-South"}}, {"music_genre": {"music_genre_id": 1073, "music_genre_parent_id": 18, "music_genre_name": "Hip-Hop", "music_genre_name_extended": "Hip Hop/Rap / Hip-Hop", "music_genre_vanity": "Hip-Hop-Rap-Hip-Hop"}}]}}, {"track_isrc": "USSM11605481", "has_lyrics": 1, "instrumental": 0, "explicit": 1, "genres": {"music_genre_list": [{"music_genre": {"music_genre_id": 1072, "music_genre_parent_id": 18, "music_genre_name": "Hardcore Rap", "music_genre_name_extended": "Hip Hop/Rap / Hardcore Rap", "music_genre_vanity": "Hip-Hop-Rap-Hardcore-Rap"}}, {"music_genre": {"music_genre_id": 18, "music_genre_parent_id": 34, "music_genre_name": "Hip Hop/Rap", "music_genre_name_extended": "Hip-Hop/Rap", "music_genre_vanity": "Hip-Hop-Rap"}}]}}, {"track_isrc": "GBBHN9000084", "has_lyrics": 1, "instrumental": 0, "explicit": 0, "genres": {"music_genre_list": [{"music_genre": {"music_genre_id": 21, "music_genre_parent_id": 34, "music_genre_name": "Rock", "music_genre_name_extended": "Rock", "music_genre_vanity": "Rock"}}]}}, {"track_isrc": "QMTAA1600043", "has_lyrics": 1, "instrumental": 0, "explicit": 0, "genres": {"music_genre_list": [{"music_genre": {"music_genre_id": 20, "music_genre_parent_id": 34, "music_genre_name": "Alternative", "music_genre_name_extended": "Alternative", "music_genre_vanity": "Alternative"}}]}}, {"track_isrc": "USSM11705125", "has_lyrics": 1, "instrumental": 0, "explicit": 0, "genres": {"music_genre_list": [{"music_genre": {"music_genre_id": 6, "music_genre_parent_id": 34, "music_genre_name": "Country", "music_genre_name_extended": "Country", "music_genre_vanity": "Country"}}]}}, {"track_isrc": "USGOT0406076", "has_lyrics": 1, "instrumental": 0, "explicit": 0, "genres": {"music_genre_list": [{"music_genre": {"music_genre_id": 1094, "music_genre_parent_id": 22, "music_genre_name": "CCM", "music_genre_name_extended": "Christian & Gospel / CCM", "music_genre_vanity": "Christian-Gospel-CCM"}}]}}, {"track_isrc": "USUM71415834", "has_lyrics": 1, "instrumental": 0, "explicit": 0, "genres": {"music_genre_list": [{"music_genre": {"music_genre_id": 17, "music_genre_parent_id": 34, "music_genre_name": "Dance", "music_genre_name_extended": "Dance", "music_genre_vanity": "Dance"}}]}}, {"track_isrc": "USCN11200248", "has_lyrics": 1, "instrumental": 0, "explicit": 0, "genres": {"music_genre_list": [{"music_genre": {"music_genre_id": 6, "music_genre_parent_id": 34, "music_genre_name": "Country", "music_genre_name_extended": "Country", "music_genre_vanity": "Country"}}]}}, {"track_isrc": "USFP71227304", "has_lyrics": 1, "instrumental": 0, "explicit": 0, "genres": {"music_genre_list": [{"music_genre": {"music_genre_id": 20, "music_genre_parent_id": 34, "music_genre_name": "Alternative", "music_genre_name_extended": "Alternative", "music_genre_vanity": "Alternative"}}]}}, {"track_isrc": "TCABN1327293", "has_lyrics": 1, "instrumental": 0, "explicit": 0, "genres": {"music_genre_list": [{"music_genre": {"music_genre_id": 14, "music_genre_parent_id": 34, "music_genre_name": "Pop", "music_genre_name_extended": "Pop", "music_genre_vanity": "Pop"}}]}}, {"track_isrc": "KRA381700254", "has_lyrics": 1, "instrumental": 0, "explicit": 0, "genres": {"music_genre_list": [{"music_genre": {"music_genre_id": 1686, "music_genre_parent_id": 1614, "music_genre_name": "K-Pop", "music_genre_name_extended": "Pop / K-Pop", "music_genre_vanity": "Pop-K-Pop"}}]}}, {"track_isrc": "USUM71411592", "has_lyrics": 1, "instrumental": 0, "explicit": 0, "genres": {"music_genre_list": [{"music_genre": {"music_genre_id": 1037, "music_genre_parent_id": 6, "music_genre_name": "Contemporary Country", "music_genre_name_extended": "Country / Contemporary Country", "music_genre_vanity": "Country-Contemporary-Country"}}, {"music_genre": {"music_genre_id": 1039, "music_genre_parent_id": 6, "music_genre_name": "Honky Tonk", "music_genre_name_extended": "Country / Honky Tonk", "music_genre_vanity": "Country-Honky-Tonk"}}, {"music_genre": {"music_genre_id": 1042, "music_genre_parent_id": 6, "music_genre_name": "Traditional Country", "music_genre_name_extended": "Country / Traditional Country", "music_genre_vanity": "Country-Traditional-Country"}}, {"music_genre": {"music_genre_id": 1133, "music_genre_parent_id": 14, "music_genre_name": "Pop/Rock", "music_genre_name_extended": "Pop / Pop/Rock", "music_genre_vanity": "Pop-Pop-Rock"}}, {"music_genre": {"music_genre_id": 6, "music_genre_parent_id": 34, "music_genre_name": "Country", "music_genre_name_extended": "Country", "music_genre_vanity": "Country"}}, {"music_genre": {"music_genre_id": 21, "music_genre_parent_id": 34, "music_genre_name": "Rock", "music_genre_name_extended": "Rock", "music_genre_vanity": "Rock"}}]}}, {"track_isrc": "USSM11705548", "has_lyrics": 1, "instrumental": 0, "explicit": 1, "genres": {"music_genre_list": [{"music_genre": {"music_genre_id": 1069, "music_genre_parent_id": 18, "music_genre_name": "Dirty South", "music_genre_name_extended": "Hip Hop/Rap / Dirty South", "music_genre_vanity": "Hip-Hop-Rap-Dirty-South"}}]}}, {"track_isrc": "USRC11502046", "has_lyrics": 1, "instrumental": 0, "explicit": 0, "genres": {"music_genre_list": [{"music_genre": {"music_genre_id": 18, "music_genre_parent_id": 34, "music_genre_name": "Hip Hop/Rap", "music_genre_name_extended": "Hip-Hop/Rap", "music_genre_vanity": "Hip-Hop-Rap"}}]}}, {"track_isrc": "USCM51100307", "has_lyrics": 1, "instrumental": 0, "explicit": 1, "genres": {"music_genre_list": [{"music_genre": {"music_genre_id": 18, "music_genre_parent_id": 34, "music_genre_name": "Hip Hop/Rap", "music_genre_name_extended": "Hip-Hop/Rap", "music_genre_vanity": "Hip-Hop-Rap"}}, {"music_genre": {"music_genre_id": 15, "music_genre_parent_id": 34, "music_genre_name": "R&B/Soul", "music_genre_name_extended": "R&B/Soul", "music_genre_vanity": "R-B-Soul"}}, {"music_genre": {"music_genre_id": 1072, "music_genre_parent_id": 18, "music_genre_name": "Hardcore Rap", "music_genre_name_extended": "Hip Hop/Rap / Hardcore Rap", "music_genre_vanity": "Hip-Hop-Rap-Hardcore-Rap"}}]}}, {"track_isrc": "QM4HH1550004", "has_lyrics": 1, "instrumental": 0, "explicit": 1, "genres": {"music_genre_list": [{"music_genre": {"music_genre_id": 18, "music_genre_parent_id": 34, "music_genre_name": "Hip Hop/Rap", "music_genre_name_extended": "Hip-Hop/Rap", "music_genre_vanity": "Hip-Hop-Rap"}}, {"music_genre": {"music_genre_id": 21, "music_genre_parent_id": 34, "music_genre_name": "Rock", "music_genre_name_extended": "Rock", "music_genre_vanity": "Rock"}}]}}, {"track_isrc": "TCACW1767742", "has_lyrics": 1, "instrumental": 0, "explicit": 1, "genres": {"music_genre_list": [{"music_genre": {"music_genre_id": 14, "music_genre_parent_id": 34, "music_genre_name": "Pop", "music_genre_name_extended": "Pop", "music_genre_vanity": "Pop"}}, {"music_genre": {"music_genre_id": 15, "music_genre_parent_id": 34, "music_genre_name": "R&B/Soul", "music_genre_name_extended": "R&B/Soul", "music_genre_vanity": "R-B-Soul"}}, {"music_genre": {"music_genre_id": 1136, "music_genre_parent_id": 15, "music_genre_name": "Contemporary R&B", "music_genre_name_extended": "R&B/Soul / Contemporary R&B", "music_genre_vanity": "R-B-Soul-Contemporary-R-B"}}]}}, {"track_isrc": "USJI10600031", "has_lyrics": 1, "instrumental": 0, "explicit": 1, "genres": {"music_genre_list": [{"music_genre": {"music_genre_id": 18, "music_genre_parent_id": 34, "music_genre_name": "Hip Hop/Rap", "music_genre_name_extended": "Hip-Hop/Rap", "music_genre_vanity": "Hip-Hop-Rap"}}]}}, {"track_isrc": "GBUM71111350", "has_lyrics": 1, "instrumental": 0, "explicit": 1, "genres": {"music_genre_list": [{"music_genre": {"music_genre_id": 14, "music_genre_parent_id": 34, "music_genre_name": "Pop", "music_genre_name_extended": "Pop", "music_genre_vanity": "Pop"}}]}}, {"track_isrc": "USCM51100305", "has_lyrics": 1, "instrumental": 0, "explicit": 1, "genres": {"music_genre_list": [{"music_genre": {"music_genre_id": 1072, "music_genre_parent_id": 18, "music_genre_name": "Hardcore Rap", "music_genre_name_extended": "Hip Hop/Rap / Hardcore Rap", "music_genre_vanity": "Hip-Hop-Rap-Hardcore-Rap"}}, {"music_genre": {"music_genre_id": 15, "music_genre_parent_id": 34, "music_genre_name": "R&B/Soul", "music_genre_name_extended": "R&B/Soul", "music_genre_vanity": "R-B-Soul"}}]}}]